README.md
setup.cfg
setup.py
echocorn/__init__.py
echocorn/__main__.py
echocorn.egg-info/PKG-INFO
echocorn.egg-info/SOURCES.txt
echocorn.egg-info/dependency_links.txt
echocorn.egg-info/entry_points.txt
echocorn.egg-info/requires.txt
echocorn.egg-info/top_level.txt