Metadata-Version: 2.4
Name: echocorn
Version: 1.0.1b0
Summary: Very fast asynchronous asgi server with HTTP/1.1 and HTTP/2.0
Home-page: https://github.com/mishakorzik/echocorn
Author: MishaKorzhik_He1Zen
Author-email: developer.mishakorzhik@gmail.com
License: Apache 2.0
Project-URL: Bug Tracker, https://github.com/mishakorzik/echocorn/issues
Project-URL: Donate, https://www.buymeacoffee.com/misakorzik
Keywords: asgi,async,uvloop,fast,http,https,hsts,tls,server,secure,secured,dualstack
Classifier: Development Status :: 4 - Beta
Classifier: License :: OSI Approved :: Apache Software License
Classifier: Operating System :: OS Independent
Classifier: Programming Language :: Python
Classifier: Programming Language :: Python :: 3
Classifier: Programming Language :: Python :: 3.7
Classifier: Programming Language :: Python :: 3.8
Classifier: Programming Language :: Python :: 3.9
Classifier: Programming Language :: Python :: 3.10
Classifier: Programming Language :: Python :: 3.11
Classifier: Programming Language :: Python :: 3.12
Classifier: Programming Language :: Python :: 3.13
Classifier: Programming Language :: Python :: 3.14
Classifier: Programming Language :: Python :: Implementation :: CPython
Classifier: Programming Language :: Python :: Implementation :: PyPy
Classifier: Framework :: AsyncIO
Classifier: Topic :: Internet :: WWW/HTTP
Classifier: Topic :: Internet :: WWW/HTTP :: Dynamic Content
Classifier: Topic :: Software Development :: Libraries :: Application Frameworks
Classifier: Environment :: Web Environment
Requires-Python: >=3.7
Requires-Dist: h2>=4.0.0
Requires-Dist: toml>=0.10.0
Dynamic: author
Dynamic: author-email
Dynamic: classifier
Dynamic: description
Dynamic: description-content-type
Dynamic: home-page
Dynamic: keywords
Dynamic: license
Dynamic: project-url
Dynamic: requires-dist
Dynamic: requires-python
Dynamic: summary
